epp_event_log_parser/__init__.py
epp_event_log_parser/epp_event_log_parser.py
epp_event_log_parser-1.0.dist-info/LICENSE
epp_event_log_parser-1.0.dist-info/METADATA
epp_event_log_parser-1.0.dist-info/WHEEL
epp_event_log_parser-1.0.dist-info/top_level.txt
epp_event_log_parser-1.0.dist-info/RECORD
