Metadata-Version: 2.1
Name: epp_event_log_parser
Version: 1.0
Summary: egg plant performance test results parser
License-File: LICENSE
